{
    "transactions": [
        {
            "date": "2019-11-30 13:09:00",
            "amount": "69.95",
            "concept": "MASSIMO DUTTI",
            "address": "Calle de Santiago",
            "location": "Valladolid",
            "category": "Confección textil en general",
            "subcategory": "Grupo Zara",
            "lat": "41.6484937",
            "lng": "-4.7293842",
            "error": null,
            "postal_code": "47001"
        },
        {
            "date": "2019-11-30 13:09:00",
            "amount": "39.95",
            "concept": "MASSIMO DUTTI",
            "address": "Calle de Santiago",
            "location": "Valladolid",
            "category": "Confección textil en general",
            "subcategory": "Grupo Zara",
            "lat": "41.6484937",
            "lng": "-4.7293842",
            "error": null,
            "postal_code": "47001"
        },
        {
            "date": "2019-11-23 15:51:00",
            "amount": "69.88",
            "concept": "LA LONJA DE TORDESILLAS",
            "address": "Avenida Valladolid",
            "location": "Tordesillas",
            "category": "Restaurantes resto",
            "subcategory": "Restaurantes resto",
            "lat": "41.5026436",
            "lng": "-4.9965524",
            "error": null,
            "postal_code": "47100"
        },
        {
            "date": "2019-11-22 15:26:00",
            "amount": "68",
            "concept": "EL CORTE INGLES-DEPARTAM.",
            "address": "",
            "location": "",
            "category": "Gran almacén ",
            "subcategory": "El Corte Inglés ",
            "lat": "0",
            "lng": "0",
            "error": null,
            "postal_code": ""
        },
        {
            "date": "2019-11-22 14:25:00",
            "amount": "79",
            "concept": "UTERQUE",
            "address": "Calle de Santiago",
            "location": "Valladolid",
            "category": "Confección textil en general",
            "subcategory": "Grupo Zara",
            "lat": "41.6487488",
            "lng": "-4.7292672",
            "error": null,
            "postal_code": "47001"
        },
        {
            "date": "2019-11-22 13:54:00",
            "amount": "109.9",
            "concept": "MASSIMO DUTTI",
            "address": "Calle de Santiago",
            "location": "Valladolid",
            "category": "Confección textil en general",
            "subcategory": "Grupo Zara",
            "lat": "41.6484937",
            "lng": "-4.7293842",
            "error": null,
            "postal_code": "47001"
        }
    ]
}
