{
    "transactionTime": "00:00:00Z",
    "detailAmount": {
        "value": 75.00,
        "currency": "EUR",
    },
    "eurAmount": {
        "value": 0.00,
        "currency": "EUR",
    },
    "bankCharge": {
        "value": 0.00,
        "currency": "EUR",
    },
    "liquidationDate": "0001-01-01",
    "liquidated": false,
    "description": "UIDO MOCASINES 5947",
    "numTarjeta": "4036 1601 0421 0077",
    "bankOperation": {
        "basicOperation": "123",
        "bankOperation": "abc",
    },
}
