{
    "beneficiary" : "beneficiary",
    "transferAmount" : {
        "value" : 35.5,
        "currency" : "EUR"
    },
    "concept" : "dinner pay",
    "currency" : "EUR",
    "dateNextExecution" : "2021-10-01",
    "dateStartValidity" : "2021-09-01",
    "dateEndValidity" : "2021-09-30",
    "IndicatorResidence" : "1",
    "actuanteCode" : "11",
    "actuanteNumber" : "11",
    "actuanteCompany" : "14",
    "iban" : "ES241111222233334444",
    "ibanBeneficiary" : "ES2711234123412341234",
    "periodicalType" : "1",
    "scheduledDayTransfer" : "1",
    "countryDestination" : "pt"
}
