<?xml version="1.0" encoding="UTF-8"?>
<datos>
    <id12345678z>
	<respuesta0>
		<soap-env:Envelope xmlns:soap-env="http://schemas.xmlsoap.org/soap/envelope/">
			<soap-env:Header />
			<soap-env:Body>
				<prefixRigel0:confirmacionIntNoSEPA_LAResponse xmlns:prefixRigel0="http://www.isban.es/webservices/TRASAN/Emisioninter_la/F_trasan_emisioninter_la/ACTRASANEmisionInter/v1">
					<methodResult>
						<referencia>004900726960044235</referencia>
						<ordenServicio>
							<CENTRO>
								<EMPRESA/>
								<CENTRO/>
							</CENTRO>
							<PRODUCTO/>
							<NUMERO_DE_ORDEN/>
						</ordenServicio>
						<retorno>PE</retorno>
					</methodResult>
				</prefixRigel0:confirmacionIntNoSEPA_LAResponse>
			</soap-env:Body>
		</soap-env:Envelope>
	</respuesta0>
	<respuesta1>
		<soap-env:Envelope xmlns:soap-env="http://schemas.xmlsoap.org/soap/envelope/">
			<soap-env:Header />
			<soap-env:Body>
				<prefixRigel0:confirmacionIntNoSEPA_LAResponse xmlns:prefixRigel0="http://www.isban.es/webservices/TRASAN/Emisioninter_la/F_trasan_emisioninter_la/ACTRASANEmisionInter/v1">
					<methodResult>
						<referencia>004900726960044235</referencia>
						<ordenServicio>
							<CENTRO>
								<EMPRESA/>
								<CENTRO/>
							</CENTRO>
							<PRODUCTO/>
							<NUMERO_DE_ORDEN/>
						</ordenServicio>
						<retorno>00</retorno>
					</methodResult>
				</prefixRigel0:confirmacionIntNoSEPA_LAResponse>
			</soap-env:Body>
		</soap-env:Envelope>
	</respuesta1>
    </id12345678z>
</datos>
