{
    "12345678z":{
        "0": {
            "telfMovil": "+34625312027   ",
            "identificadorContrato": {
                "centro": {
                    "empresa": "0049",
                    "centro": "0017"
                },
                "subgrupo": "764",
                "numerodecontrato": "0001625"
            },
            "fechaAlta": "2020-01-22T17:19:31.637+0000",
            "fechaFinVigencia": "9999-12-31T23:16:38.999+0000",
            "retorno": "00",
            "mensaje": null,
            "codIBAN": {
                "pais": "ES",
                "digitodecontrol": "19",
                "codbban": "00490075462116810385          "
            },
            "offset": "0006",
            "estadoOffset": "A",
            "indMigrad": "S",
            "xpan": "9724020260000199      "
        },
        "1": {
            "appName": "movpar-bizum-operativa-ms",
            "timeStamp": 1629787404323,
            "errorName": "OJ0001                                  ",
            "status": 404,
            "internalCode": 404,
            "shortMessage": "Not Found",
            "detailedMessage": "The URI requested is invalid or the resource requested does not exists."
        }
    }
}
